MANIFEST.in
README.rst
setup.py
django_seleniumhelpers.egg-info/PKG-INFO
django_seleniumhelpers.egg-info/SOURCES.txt
django_seleniumhelpers.egg-info/dependency_links.txt
django_seleniumhelpers.egg-info/not-zip-safe
django_seleniumhelpers.egg-info/pbr.json
django_seleniumhelpers.egg-info/requires.txt
django_seleniumhelpers.egg-info/top_level.txt
seleniumhelpers/__init__.py
seleniumhelpers/models.py
seleniumhelpers/seleniumhelpers.py
seleniumhelpers/management/__init__.py
seleniumhelpers/management/commands/__init__.py
seleniumhelpers/management/commands/listseleniumbrowsers.py