Metadata-Version: 1.1
Name: django-seleniumhelpers
Version: 1.1.2
Summary: Extends django.test.LiveServerTestCase to make selenium testing even easier.
Home-page: https://github.com/espenak/django_seleniumhelpers
Author: Espen Angell Kristiansen
Author-email: post@espenak.net
License: BSD
Platform: UNKNOWN
Classifier: Development Status :: 5 - Production/Stable
Classifier: Environment :: Web Environment
Classifier: Framework :: Django
Classifier: Intended Audience :: Developers
Classifier: License :: OSI Approved
Classifier: Operating System :: OS Independent
Classifier: Programming Language :: Python
